argo/__init__.py
argo/agent.py
argo/cli.py
argo/client.py
argo/context.py
argo/crew.py
argo/declarative.py
argo/llm.py
argo/prompts.py
argo/resolver.py
argo/server.py
argo/skills.py
argo/tools.py
argo/utils.py
argo_ai-0.4.2.dist-info/METADATA
argo_ai-0.4.2.dist-info/WHEEL
argo_ai-0.4.2.dist-info/entry_points.txt
argo_ai-0.4.2.dist-info/licenses/LICENSE
argo_ai-0.4.2.dist-info/RECORD
