Metadata-Version: 2.4
Name: argo-ai
Version: 0.4.2
Summary: Agent-based Reasoning, Governance, and Orchestration
License-File: LICENSE
Requires-Python: >=3.13
Requires-Dist: openai>=1.76.0
Requires-Dist: pydantic>=2.11.3
Requires-Dist: pyyaml>=6.0.2
Requires-Dist: rich>=14.0.0
Requires-Dist: typer>=0.15.3
